{
"meta":{"test_sets":["test"],"test_metrics":[{"best_value":"Min","name":"LogTargetsRmsleMetric"}],"learn_metrics":[{"best_value":"Min","name":"LogTargetsRmsleMetric"}],"launch_mode":"Train","parameters":"","iteration_count":800,"learn_sets":["learn"],"name":"experiment"},
"iterations":[
{"learn":[1.858545276],"iteration":0,"passed_time":0.1500827482,"remaining_time":119.9161158,"test":[1.816094209]},
{"learn":[1.818347732],"iteration":1,"passed_time":0.3240928529,"remaining_time":129.3130483,"test":[1.776003105]},
{"learn":[1.779670061],"iteration":2,"passed_time":0.4946840623,"remaining_time":131.4210659,"test":[1.737426156]},
{"learn":[1.740237979],"iteration":3,"passed_time":0.669602562,"remaining_time":133.2509098,"test":[1.698097935]},
{"learn":[1.706138281],"iteration":4,"passed_time":0.8393586104,"remaining_time":133.4580191,"test":[1.663796599]},
{"learn":[1.671542613],"iteration":5,"passed_time":1.008340551,"remaining_time":133.4370662,"test":[1.629435311]},
{"learn":[1.638438081],"iteration":6,"passed_time":1.173981828,"remaining_time":132.9953699,"test":[1.596448743]},
{"learn":[1.605571369],"iteration":7,"passed_time":1.346252132,"remaining_time":133.278961,"test":[1.56337162]},
{"learn":[1.573952099],"iteration":8,"passed_time":1.516866919,"remaining_time":133.3157481,"test":[1.531623612]},
{"learn":[1.544441044],"iteration":9,"passed_time":1.681592162,"remaining_time":132.8457808,"test":[1.502280468]},
{"learn":[1.515234484],"iteration":10,"passed_time":1.852439957,"remaining_time":132.870466,"test":[1.472917249]},
{"learn":[1.487257423],"iteration":11,"passed_time":2.020609162,"remaining_time":132.6866683,"test":[1.444748128]},
{"learn":[1.460534384],"iteration":12,"passed_time":2.186797273,"remaining_time":132.3853426,"test":[1.418365332]},
{"learn":[1.434672752],"iteration":13,"passed_time":2.264587082,"remaining_time":127.140389,"test":[1.392370177]},
{"learn":[1.408802194],"iteration":14,"passed_time":2.419984863,"remaining_time":126.6458745,"test":[1.366594093]},
{"learn":[1.385648905],"iteration":15,"passed_time":2.585299457,"remaining_time":126.6796734,"test":[1.343581011]},
{"learn":[1.361748345],"iteration":16,"passed_time":2.746160309,"remaining_time":126.484913,"test":[1.319891911]},
{"learn":[1.339856365],"iteration":17,"passed_time":2.906393766,"remaining_time":126.2666625,"test":[1.297873744]},
{"learn":[1.317992604],"iteration":18,"passed_time":3.07171085,"remaining_time":126.2634828,"test":[1.276329273]},
{"learn":[1.295725553],"iteration":19,"passed_time":3.239827873,"remaining_time":126.353287,"test":[1.254393854]},
{"learn":[1.27604956],"iteration":20,"passed_time":3.40970285,"remaining_time":126.4837391,"test":[1.234862711]},
{"learn":[1.258063458],"iteration":21,"passed_time":3.578082675,"remaining_time":126.5340146,"test":[1.217130243]},
{"learn":[1.240312924],"iteration":22,"passed_time":3.74970848,"remaining_time":126.6749343,"test":[1.199292677]},
{"learn":[1.222282553],"iteration":23,"passed_time":3.921096492,"remaining_time":126.7821199,"test":[1.181502543]},
{"learn":[1.205362377],"iteration":24,"passed_time":4.092402078,"remaining_time":126.8644644,"test":[1.16489008]},
{"learn":[1.190261122],"iteration":25,"passed_time":4.25805651,"remaining_time":126.7590669,"test":[1.149704279]},
{"learn":[1.174829351],"iteration":26,"passed_time":4.422705398,"remaining_time":126.6204175,"test":[1.134526506]},
{"learn":[1.159113615],"iteration":27,"passed_time":4.589821081,"remaining_time":126.5479241,"test":[1.117809431]},
{"learn":[1.144353574],"iteration":28,"passed_time":4.750973248,"remaining_time":126.3103577,"test":[1.103340791]},
{"learn":[1.130627353],"iteration":29,"passed_time":4.919147574,"remaining_time":126.2581211,"test":[1.089987985]},
{"learn":[1.118667393],"iteration":30,"passed_time":5.082658423,"remaining_time":126.0827202,"test":[1.077952942]},
{"learn":[1.105292729],"iteration":31,"passed_time":5.247115709,"remaining_time":125.930777,"test":[1.064874903]},
{"learn":[1.093329069],"iteration":32,"passed_time":5.424426766,"remaining_time":126.0768282,"test":[1.052843282]},
{"learn":[1.083146445],"iteration":33,"passed_time":5.591497316,"remaining_time":125.9731454,"test":[1.042367587]},
{"learn":[1.072927331],"iteration":34,"passed_time":5.763834404,"remaining_time":125.980952,"test":[1.03233921]},
{"learn":[1.062430695],"iteration":35,"passed_time":5.933021634,"remaining_time":125.9119036,"test":[1.020713744]},
{"learn":[1.052536959],"iteration":36,"passed_time":6.106422111,"remaining_time":125.9243262,"test":[1.010883849]},
{"learn":[1.042881031],"iteration":37,"passed_time":6.277011767,"remaining_time":125.8706044,"test":[1.001058869]},
{"learn":[1.033639225],"iteration":38,"passed_time":6.446626877,"remaining_time":125.7918732,"test":[0.9919254199]},
{"learn":[1.025028904],"iteration":39,"passed_time":6.615002891,"remaining_time":125.6850549,"test":[0.9836327844]},
{"learn":[1.017271158],"iteration":40,"passed_time":6.784559499,"remaining_time":125.5970893,"test":[0.9762390087]},
{"learn":[1.01021485],"iteration":41,"passed_time":6.950477504,"remaining_time":125.4395702,"test":[0.9693659659]},
{"learn":[1.002972833],"iteration":42,"passed_time":7.122706282,"remaining_time":125.3927594,"test":[0.9621684217]},
{"learn":[0.9949783014],"iteration":43,"passed_time":7.288803703,"remaining_time":125.2349,"test":[0.9544651394]},
{"learn":[0.9888777085],"iteration":44,"passed_time":7.459376315,"remaining_time":125.1517582,"test":[0.9486074279]},
{"learn":[0.9822265623],"iteration":45,"passed_time":7.629271099,"remaining_time":125.0537045,"test":[0.9418222943]},
{"learn":[0.97637381],"iteration":46,"passed_time":7.798766845,"remaining_time":124.9462007,"test":[0.9360518297]},
{"learn":[0.970438006],"iteration":47,"passed_time":7.97138232,"remaining_time":124.8849897,"test":[0.9303808789]},
{"learn":[0.9623255113],"iteration":48,"passed_time":8.136013519,"remaining_time":124.6968603,"test":[0.9220052155]},
{"learn":[0.9564940934],"iteration":49,"passed_time":8.305916885,"remaining_time":124.5887533,"test":[0.9164041131]},
{"learn":[0.9517376125],"iteration":50,"passed_time":8.476992079,"remaining_time":124.4954327,"test":[0.9119771805]},
{"learn":[0.9468668566],"iteration":51,"passed_time":8.646696218,"remaining_time":124.3793994,"test":[0.9074800795]},
{"learn":[0.9421731335],"iteration":52,"passed_time":8.810524233,"remaining_time":124.1785208,"test":[0.9030920761]},
{"learn":[0.9374338053],"iteration":53,"passed_time":8.978031787,"remaining_time":124.0298465,"test":[0.8984855684]},
{"learn":[0.9328720542],"iteration":54,"passed_time":9.147307593,"remaining_time":123.9044392,"test":[0.8942697944]},
{"learn":[0.9261466824],"iteration":55,"passed_time":9.317781278,"remaining_time":123.7933798,"test":[0.887389962]},
{"learn":[0.9224702815],"iteration":56,"passed_time":9.491726524,"remaining_time":123.7254879,"test":[0.8833756797]},
{"learn":[0.9185975521],"iteration":57,"passed_time":9.663994777,"remaining_time":123.6324849,"test":[0.8795145887]},
{"learn":[0.9151095831],"iteration":58,"passed_time":9.834979842,"remaining_time":123.520679,"test":[0.8762907416]},
{"learn":[0.9120313263],"iteration":59,"passed_time":10.0153315,"remaining_time":123.5224218,"test":[0.8728873412]},
{"learn":[0.9061176596],"iteration":60,"passed_time":10.18462231,"remaining_time":123.3841948,"test":[0.8674923375]},
{"learn":[0.902950898],"iteration":61,"passed_time":10.35597944,"remaining_time":123.2695618,"test":[0.8644506609]},
{"learn":[0.9000346617],"iteration":62,"passed_time":10.52723083,"remaining_time":123.1518908,"test":[0.8616278445]},
{"learn":[0.8952540506],"iteration":63,"passed_time":10.69662979,"remaining_time":123.0112425,"test":[0.8565721006]},
{"learn":[0.8901769898],"iteration":64,"passed_time":10.86502531,"remaining_time":122.8583631,"test":[0.8516287746]},
{"learn":[0.8855233676],"iteration":65,"passed_time":11.04322945,"remaining_time":122.8140972,"test":[0.8474353225]},
{"learn":[0.8830226391],"iteration":66,"passed_time":11.20684591,"remaining_time":122.6062396,"test":[0.8452345572]},
{"learn":[0.8805189318],"iteration":67,"passed_time":11.36873125,"remaining_time":122.3810482,"test":[0.8430437511]},
{"learn":[0.8762569361],"iteration":68,"passed_time":11.54271663,"remaining_time":122.285882,"test":[0.8390964012]},
{"learn":[0.8743941558],"iteration":69,"passed_time":11.71277292,"remaining_time":122.147489,"test":[0.8372684578]},
{"learn":[0.8720071198],"iteration":70,"passed_time":11.88085382,"remaining_time":121.9879216,"test":[0.8351534365]},
{"learn":[0.8682338511],"iteration":71,"passed_time":12.04995594,"remaining_time":121.8384434,"test":[0.8313820214]},
{"learn":[0.8663753543],"iteration":72,"passed_time":12.2214265,"remaining_time":121.7120146,"test":[0.8295876413]},
{"learn":[0.8625913551],"iteration":73,"passed_time":12.39385626,"remaining_time":121.593779,"test":[0.8262383494]},
{"learn":[0.8606966692],"iteration":74,"passed_time":12.56345255,"remaining_time":121.446708,"test":[0.8245527139]},
{"learn":[0.8591209766],"iteration":75,"passed_time":12.73028192,"remaining_time":121.2726857,"test":[0.8230350641]},
{"learn":[0.8562182159],"iteration":76,"passed_time":12.90148496,"remaining_time":121.1399172,"test":[0.8202146975]},
{"learn":[0.8534669091],"iteration":77,"passed_time":13.06765659,"remaining_time":120.9595905,"test":[0.8176962841]},
{"learn":[0.851879079],"iteration":78,"passed_time":13.23359822,"remaining_time":120.777523,"test":[0.8163874794]},
{"learn":[0.8490688093],"iteration":79,"passed_time":13.40711051,"remaining_time":120.6639946,"test":[0.8135929521]},
{"learn":[0.8479987769],"iteration":80,"passed_time":13.57292571,"remaining_time":120.4806615,"test":[0.812706625]},
{"learn":[0.8454068407],"iteration":81,"passed_time":13.7429332,"remaining_time":120.3344639,"test":[0.8101464074]},
{"learn":[0.8430813876],"iteration":82,"passed_time":13.90923341,"remaining_time":120.1556669,"test":[0.808455214]},
{"learn":[0.841773877],"iteration":83,"passed_time":14.07615189,"remaining_time":119.9824375,"test":[0.8073055025]},
{"learn":[0.8393777272],"iteration":84,"passed_time":14.24057619,"remaining_time":119.7883762,"test":[0.8051909882]},
{"learn":[0.8383048504],"iteration":85,"passed_time":14.41229199,"remaining_time":119.6555405,"test":[0.8043667285]},
{"learn":[0.8363251848],"iteration":86,"passed_time":14.5766755,"remaining_time":119.4617199,"test":[0.8024510513]},
{"learn":[0.8354797123],"iteration":87,"passed_time":14.74690903,"remaining_time":119.3159004,"test":[0.8017340198]},
{"learn":[0.8333349344],"iteration":88,"passed_time":14.91865282,"remaining_time":119.1815972,"test":[0.7996213684]},
{"learn":[0.8322741276],"iteration":89,"passed_time":15.08451155,"remaining_time":119.0000356,"test":[0.7987841331]},
{"learn":[0.830431403],"iteration":90,"passed_time":15.25143564,"remaining_time":118.8271194,"test":[0.796900851]},
{"learn":[0.8284371067],"iteration":91,"passed_time":15.4230857,"remaining_time":118.690703,"test":[0.7950091857]},
{"learn":[0.8275195481],"iteration":92,"passed_time":15.59512233,"remaining_time":118.5564676,"test":[0.7942536458]},
{"learn":[0.825601429],"iteration":93,"passed_time":15.7642909,"remaining_time":118.399887,"test":[0.7926785976]},
{"learn":[0.8237617427],"iteration":94,"passed_time":15.93456553,"remaining_time":118.2512495,"test":[0.7911089182]},
{"learn":[0.8226560606],"iteration":95,"passed_time":16.11095805,"remaining_time":118.1470257,"test":[0.7902388212]},
{"learn":[0.8210174217],"iteration":96,"passed_time":16.28597606,"remaining_time":118.0313523,"test":[0.7886201279]},
{"learn":[0.8201926538],"iteration":97,"passed_time":16.45547954,"remaining_time":117.8749657,"test":[0.788016509]},
{"learn":[0.8194567076],"iteration":98,"passed_time":16.62931962,"remaining_time":117.7490208,"test":[0.7875773794]},
{"learn":[0.8187504078],"iteration":99,"passed_time":16.79431214,"remaining_time":117.5601849,"test":[0.7869057591]},
{"learn":[0.8174487188],"iteration":100,"passed_time":16.96338983,"remaining_time":117.400094,"test":[0.7856386178]},
{"learn":[0.8159878044],"iteration":101,"passed_time":17.1354476,"remaining_time":117.2602198,"test":[0.784514909]},
{"learn":[0.8144533837],"iteration":102,"passed_time":17.31219921,"remaining_time":117.1514839,"test":[0.7830027025]},
{"learn":[0.813265592],"iteration":103,"passed_time":17.48095913,"remaining_time":116.9879572,"test":[0.781874767]},
{"learn":[0.8120923324],"iteration":104,"passed_time":17.65170029,"remaining_time":116.8374448,"test":[0.7808574499]},
{"learn":[0.8109865542],"iteration":105,"passed_time":17.81762556,"remaining_time":116.6550202,"test":[0.7800382437]},
{"learn":[0.810480442],"iteration":106,"passed_time":17.98829998,"remaining_time":116.5036625,"test":[0.7796117881]},
{"learn":[0.8099985649],"iteration":107,"passed_time":18.15989251,"remaining_time":116.3578298,"test":[0.7791738459]},
{"learn":[0.8094207214],"iteration":108,"passed_time":18.3345114,"remaining_time":116.2307099,"test":[0.7786646449]},
{"learn":[0.809068196],"iteration":109,"passed_time":18.50411044,"remaining_time":116.0712382,"test":[0.7784006318]},
{"learn":[0.807750444],"iteration":110,"passed_time":18.6758768,"remaining_time":115.9250371,"test":[0.7773581503]},
{"learn":[0.8074493946],"iteration":111,"passed_time":18.84353863,"remaining_time":115.7531659,"test":[0.77707113]},
{"learn":[0.8069490215],"iteration":112,"passed_time":19.01023415,"remaining_time":115.5754944,"test":[0.7766506574]},
{"learn":[0.8058605635],"iteration":113,"passed_time":19.18214502,"remaining_time":115.429399,"test":[0.77563602]},
{"learn":[0.8050265449],"iteration":114,"passed_time":19.35237462,"remaining_time":115.2728401,"test":[0.7749171246]},
{"learn":[0.8045519469],"iteration":115,"passed_time":19.51660075,"remaining_time":115.0806458,"test":[0.77460638]},
{"learn":[0.8036256381],"iteration":116,"passed_time":19.68279568,"remaining_time":114.9004227,"test":[0.7738687892]},
{"learn":[0.8029243632],"iteration":117,"passed_time":19.84511752,"remaining_time":114.6980521,"test":[0.7729764909]},
{"learn":[0.8021140506],"iteration":118,"passed_time":20.01775258,"remaining_time":114.555374,"test":[0.772235799]},
{"learn":[0.8017386455],"iteration":119,"passed_time":20.1921753,"remaining_time":114.4223267,"test":[0.772025745]},
{"learn":[0.8012915962],"iteration":120,"passed_time":20.36015514,"remaining_time":114.2524408,"test":[0.7716851263]},
{"learn":[0.8009108764],"iteration":121,"passed_time":20.5298792,"remaining_time":114.0922795,"test":[0.7713821825]},
{"learn":[0.8005014198],"iteration":122,"passed_time":20.69525259,"remaining_time":113.9080163,"test":[0.7711235356]},
{"learn":[0.799642401],"iteration":123,"passed_time":20.86601813,"remaining_time":113.7534537,"test":[0.770201329]},
{"learn":[0.7994269193],"iteration":124,"passed_time":21.04019001,"remaining_time":113.6170261,"test":[0.7700591021]},
{"learn":[0.7992500121],"iteration":125,"passed_time":21.2110278,"remaining_time":113.4621646,"test":[0.770002319]},
{"learn":[0.7989855117],"iteration":126,"passed_time":21.38116803,"remaining_time":113.303355,"test":[0.7697490893]},
{"learn":[0.7985849146],"iteration":127,"passed_time":21.55195815,"remaining_time":113.1477803,"test":[0.7694044186]},
{"learn":[0.7978759152],"iteration":128,"passed_time":21.72122486,"remaining_time":112.9840456,"test":[0.768655292]},
{"learn":[0.7973626617],"iteration":129,"passed_time":21.88492343,"remaining_time":112.7915284,"test":[0.7682633589]},
{"learn":[0.7971432611],"iteration":130,"passed_time":22.04914745,"remaining_time":112.6021347,"test":[0.7682423635]},
{"learn":[0.7967724238],"iteration":131,"passed_time":22.22217957,"remaining_time":112.4576966,"test":[0.7679018667]},
{"learn":[0.7959229002],"iteration":132,"passed_time":22.39558868,"remaining_time":112.3147192,"test":[0.7671712094]},
{"learn":[0.7953267196],"iteration":133,"passed_time":22.56477566,"remaining_time":112.1503029,"test":[0.7666477471]},
{"learn":[0.7950307776],"iteration":134,"passed_time":22.73057476,"remaining_time":111.9691275,"test":[0.7664771238]},
{"learn":[0.7944848031],"iteration":135,"passed_time":22.89995219,"remaining_time":111.8056489,"test":[0.7658715374]},
{"learn":[0.7939543134],"iteration":136,"passed_time":23.06589122,"remaining_time":111.6254444,"test":[0.7652246087]},
{"learn":[0.7933660105],"iteration":137,"passed_time":23.23607511,"remaining_time":111.4658096,"test":[0.7646444879]},
{"learn":[0.7927603294],"iteration":138,"passed_time":23.40377354,"remaining_time":111.2942037,"test":[0.7640909427]},
{"learn":[0.792158532],"iteration":139,"passed_time":23.56996122,"remaining_time":111.1155314,"test":[0.763587765]},
{"learn":[0.7915744401],"iteration":140,"passed_time":23.74143937,"remaining_time":110.9617627,"test":[0.7630956045]},
{"learn":[0.7911347289],"iteration":141,"passed_time":23.90655316,"remaining_time":110.7782534,"test":[0.7626638422]},
{"learn":[0.7906437218],"iteration":142,"passed_time":24.07460659,"remaining_time":110.6085072,"test":[0.7621983036]},
{"learn":[0.7902361576],"iteration":143,"passed_time":24.24484111,"remaining_time":110.4487206,"test":[0.7618849509]},
{"learn":[0.7898669601],"iteration":144,"passed_time":24.41734394,"remaining_time":110.2990364,"test":[0.7615790265]},
{"learn":[0.7896787434],"iteration":145,"passed_time":24.58328474,"remaining_time":110.1196454,"test":[0.7614612804]},
{"learn":[0.789550859],"iteration":146,"passed_time":24.762607,"remaining_time":109.9998801,"test":[0.761392821]},
{"learn":[0.789281018],"iteration":147,"passed_time":24.93412982,"remaining_time":109.8449503,"test":[0.7611666293]},
{"learn":[0.7888840243],"iteration":148,"passed_time":25.10498264,"remaining_time":109.6868705,"test":[0.7607869994]},
{"learn":[0.788712606],"iteration":149,"passed_time":25.27438079,"remaining_time":109.5223168,"test":[0.7607384323]},
{"learn":[0.788464172],"iteration":150,"passed_time":25.4427793,"remaining_time":109.3534024,"test":[0.7604427847]},
{"learn":[0.7880382033],"iteration":151,"passed_time":25.62008785,"remaining_time":109.2224798,"test":[0.7600242458]},
{"learn":[0.7877757708],"iteration":152,"passed_time":25.78898321,"remaining_time":109.0553734,"test":[0.7598511584]},
{"learn":[0.7873256637],"iteration":153,"passed_time":25.95525324,"remaining_time":108.8772311,"test":[0.7594978119]},
{"learn":[0.7868382317],"iteration":154,"passed_time":26.12274942,"remaining_time":108.7043444,"test":[0.7590405796]},
{"learn":[0.7865168246],"iteration":155,"passed_time":26.2898648,"remaining_time":108.5299547,"test":[0.758696536]},
{"learn":[0.7860516874],"iteration":156,"passed_time":26.46302773,"remaining_time":108.3804257,"test":[0.7582935739]},
{"learn":[0.7856685839],"iteration":157,"passed_time":26.63623627,"remaining_time":108.2307828,"test":[0.7578908889]},
{"learn":[0.7854211883],"iteration":158,"passed_time":26.805973,"remaining_time":108.0668471,"test":[0.7578031045]},
{"learn":[0.785162912],"iteration":159,"passed_time":26.97292464,"remaining_time":107.8916986,"test":[0.7576217845]},
{"learn":[0.7846642185],"iteration":160,"passed_time":27.14623363,"remaining_time":107.7418838,"test":[0.7572909477]},
{"learn":[0.7843994892],"iteration":161,"passed_time":27.31576681,"remaining_time":107.5769088,"test":[0.7571209082]},
{"learn":[0.7839568536],"iteration":162,"passed_time":27.48804289,"remaining_time":107.4225971,"test":[0.7567499279]},
{"learn":[0.7835224626],"iteration":163,"passed_time":27.66007318,"remaining_time":107.2671131,"test":[0.7563443127]},
{"learn":[0.7832522306],"iteration":164,"passed_time":27.82846232,"remaining_time":107.0974156,"test":[0.7561706301]},
{"learn":[0.7829107659],"iteration":165,"passed_time":28.00022405,"remaining_time":106.9406148,"test":[0.7558293085]},
{"learn":[0.7826211497],"iteration":166,"passed_time":28.16752935,"remaining_time":106.766743,"test":[0.7556241478]},
{"learn":[0.7824420273],"iteration":167,"passed_time":28.33429773,"remaining_time":106.5909296,"test":[0.755469531]},
{"learn":[0.7821434441],"iteration":168,"passed_time":28.49998016,"remaining_time":106.4111685,"test":[0.7553123563]},
{"learn":[0.7820013192],"iteration":169,"passed_time":28.66804323,"remaining_time":106.2403955,"test":[0.7552629453]},
{"learn":[0.7818472476],"iteration":170,"passed_time":28.83431556,"remaining_time":106.0630672,"test":[0.7550683911]},
{"learn":[0.781561188],"iteration":171,"passed_time":29.00290563,"remaining_time":105.8943299,"test":[0.7548521958]},
{"learn":[0.7814220976],"iteration":172,"passed_time":29.16720486,"remaining_time":105.7100431,"test":[0.7548068186]},
{"learn":[0.7811729664],"iteration":173,"passed_time":29.33477929,"remaining_time":105.5377692,"test":[0.7545986723]},
{"learn":[0.7809229083],"iteration":174,"passed_time":29.50407437,"remaining_time":105.3716942,"test":[0.7543275204]},
{"learn":[0.7807141235],"iteration":175,"passed_time":29.67243557,"remaining_time":105.2022716,"test":[0.7541280499]},
{"learn":[0.7806732193],"iteration":176,"passed_time":29.84346666,"remaining_time":105.0422583,"test":[0.7541353291]},
{"learn":[0.7805729573],"iteration":177,"passed_time":30.01601732,"remaining_time":104.8874313,"test":[0.7540435859]},
{"learn":[0.7802104868],"iteration":178,"passed_time":30.18574389,"remaining_time":104.7226087,"test":[0.7537713673]},
{"learn":[0.7801574397],"iteration":179,"passed_time":30.35260537,"remaining_time":104.5478629,"test":[0.7537848909]},
{"learn":[0.7798878007],"iteration":180,"passed_time":30.52295881,"remaining_time":104.3851464,"test":[0.7536394973]},
{"learn":[0.7795821436],"iteration":181,"passed_time":30.695199,"remaining_time":104.2287527,"test":[0.7533456834]},
{"learn":[0.7794693202],"iteration":182,"passed_time":30.86691344,"remaining_time":104.0704131,"test":[0.7532917792]},
{"learn":[0.7793492629],"iteration":183,"passed_time":31.03396865,"remaining_time":103.8963298,"test":[0.7532598287]},
{"learn":[0.7791368171],"iteration":184,"passed_time":31.20371476,"remaining_time":103.731268,"test":[0.7530825576]},
{"learn":[0.7790618448],"iteration":185,"passed_time":31.37564488,"remaining_time":103.5733654,"test":[0.7530922209]},
{"learn":[0.7789292121],"iteration":186,"passed_time":31.55106903,"remaining_time":103.4267664,"test":[0.7529885208]},
{"learn":[0.7787769135],"iteration":187,"passed_time":31.72638373,"remaining_time":103.2795045,"test":[0.7529037296]},
{"learn":[0.7786638184],"iteration":188,"passed_time":31.89642424,"remaining_time":103.1148953,"test":[0.7527943862]},
{"learn":[0.7784588225],"iteration":189,"passed_time":32.06638117,"remaining_time":102.9499606,"test":[0.752658748]},
{"learn":[0.7782582045],"iteration":190,"passed_time":32.26084494,"remaining_time":102.8631129,"test":[0.7525660897]},
{"learn":[0.7781546085],"iteration":191,"passed_time":32.43010517,"remaining_time":102.695333,"test":[0.7525004941]},
{"learn":[0.7780705789],"iteration":192,"passed_time":32.59683632,"remaining_time":102.5195837,"test":[0.752467948]},
{"learn":[0.7780077256],"iteration":193,"passed_time":32.76161126,"remaining_time":102.3378166,"test":[0.7524351388]},
{"learn":[0.7778360652],"iteration":194,"passed_time":32.93086253,"remaining_time":102.170112,"test":[0.7522828262]},
{"learn":[0.7777040569],"iteration":195,"passed_time":33.1002279,"remaining_time":102.0027431,"test":[0.752168015]},
{"learn":[0.7775732502],"iteration":196,"passed_time":33.27507394,"remaining_time":101.8521299,"test":[0.7520427696]},
{"learn":[0.7774603374],"iteration":197,"passed_time":33.44639894,"remaining_time":101.6905665,"test":[0.7519510395]},
{"learn":[0.7773806204],"iteration":198,"passed_time":33.61701199,"remaining_time":101.5267548,"test":[0.7519536169]},
{"learn":[0.7772468673],"iteration":199,"passed_time":33.78212324,"remaining_time":101.3463697,"test":[0.7519829502]},
{"learn":[0.7771037405],"iteration":200,"passed_time":33.95520828,"remaining_time":101.1898993,"test":[0.7518746925]},
{"learn":[0.7768558518],"iteration":201,"passed_time":34.12686541,"remaining_time":101.0290372,"test":[0.7517409765]},
{"learn":[0.7768124584],"iteration":202,"passed_time":34.304304,"remaining_time":100.8850714,"test":[0.7517330644]},
{"learn":[0.7765728405],"iteration":203,"passed_time":34.47829489,"remaining_time":100.7307047,"test":[0.7514929678]},
{"learn":[0.7764557227],"iteration":204,"passed_time":34.64580486,"remaining_time":100.5573361,"test":[0.7513951285]},
{"learn":[0.7762883827],"iteration":205,"passed_time":34.81044069,"remaining_time":100.3757367,"test":[0.7513053074]},
{"learn":[0.7761983969],"iteration":206,"passed_time":34.98432312,"remaining_time":100.2207904,"test":[0.7512261981]},
{"learn":[0.7759439892],"iteration":207,"passed_time":35.15530168,"remaining_time":100.0573971,"test":[0.7509389281]},
{"learn":[0.7758557157],"iteration":208,"passed_time":35.32566053,"remaining_time":99.89217882,"test":[0.7509185988]},
{"learn":[0.7756908709],"iteration":209,"passed_time":35.49496375,"remaining_time":99.72394578,"test":[0.7508774631]},
{"learn":[0.7755585411],"iteration":210,"passed_time":35.66434058,"remaining_time":99.55590807,"test":[0.7507730904]},
{"learn":[0.7754904773],"iteration":211,"passed_time":35.83053502,"remaining_time":99.37903108,"test":[0.7507041932]},
{"learn":[0.7753933736],"iteration":212,"passed_time":36.0019617,"remaining_time":99.21667379,"test":[0.7507005554]},
{"learn":[0.7753090168],"iteration":213,"passed_time":36.17241251,"remaining_time":99.05155948,"test":[0.7507091763]},
{"learn":[0.7750704883],"iteration":214,"passed_time":36.34493281,"remaining_time":98.89202649,"test":[0.7505210237]},
{"learn":[0.7749146679],"iteration":215,"passed_time":36.51137727,"remaining_time":98.71594595,"test":[0.750382607]},
{"learn":[0.7747693206],"iteration":216,"passed_time":36.68957075,"remaining_time":98.57151958,"test":[0.7502552675]},
{"learn":[0.7746102327],"iteration":217,"passed_time":36.86113117,"remaining_time":98.40907496,"test":[0.7502024937]},
{"learn":[0.7744284295],"iteration":218,"passed_time":37.02923595,"remaining_time":98.23737939,"test":[0.7501308797]},
{"learn":[0.7742597253],"iteration":219,"passed_time":37.19954138,"remaining_time":98.07151819,"test":[0.7499966593]},
{"learn":[0.7739807366],"iteration":220,"passed_time":37.36943788,"remaining_time":97.90454538,"test":[0.7497315417]},
{"learn":[0.7738747953],"iteration":221,"passed_time":37.5409708,"remaining_time":97.74180686,"test":[0.7496716677]},
{"learn":[0.773820296],"iteration":222,"passed_time":37.70856917,"remaining_time":97.56880902,"test":[0.7495907313]},
{"learn":[0.7737337333],"iteration":223,"passed_time":37.87742795,"remaining_time":97.39910044,"test":[0.7495817985]},
{"learn":[0.7734838391],"iteration":224,"passed_time":38.04083892,"remaining_time":97.21547723,"test":[0.7495041084]},
{"learn":[0.7733682396],"iteration":225,"passed_time":38.20699313,"remaining_time":97.03900025,"test":[0.7494534255]},
{"learn":[0.773240752],"iteration":226,"passed_time":38.37729568,"remaining_time":96.87308556,"test":[0.7494298477]},
{"learn":[0.7730431185],"iteration":227,"passed_time":38.53897577,"remaining_time":96.6855006,"test":[0.7492942828]},
{"learn":[0.7729464026],"iteration":228,"passed_time":38.70883085,"remaining_time":96.51852583,"test":[0.7493220024]},
{"learn":[0.7727806969],"iteration":229,"passed_time":38.879159,"remaining_time":96.35269839,"test":[0.7492597795]},
{"learn":[0.7727175279],"iteration":230,"passed_time":39.05514286,"remaining_time":96.20076314,"test":[0.7492840651]},
{"learn":[0.7726404566],"iteration":231,"passed_time":39.2195014,"remaining_time":96.02015859,"test":[0.7492696844]},
{"learn":[0.772468222],"iteration":232,"passed_time":39.39407354,"remaining_time":95.86454805,"test":[0.7491499987]},
{"learn":[0.7723494043],"iteration":233,"passed_time":39.56237435,"remaining_time":95.69360633,"test":[0.7490555474]},
{"learn":[0.7722171342],"iteration":234,"passed_time":39.73340242,"remaining_time":95.52924412,"test":[0.7489078671]},
{"learn":[0.7720516928],"iteration":235,"passed_time":39.89800398,"remaining_time":95.34946714,"test":[0.7487597799]},
{"learn":[0.7719489389],"iteration":236,"passed_time":40.06102482,"remaining_time":95.16606317,"test":[0.7486447932]},
{"learn":[0.7718330449],"iteration":237,"passed_time":40.22623148,"remaining_time":94.98799199,"test":[0.748568251]},
{"learn":[0.7716182932],"iteration":238,"passed_time":40.39552379,"remaining_time":94.81961861,"test":[0.7483698344]},
{"learn":[0.7714457414],"iteration":239,"passed_time":40.55989871,"remaining_time":94.63976366,"test":[0.7482168816]},
{"learn":[0.7713132741],"iteration":240,"passed_time":40.72321832,"remaining_time":94.45758937,"test":[0.7481752495]},
{"learn":[0.7711849292],"iteration":241,"passed_time":40.89294016,"remaining_time":94.29033309,"test":[0.7480407657]},
{"learn":[0.7709665886],"iteration":242,"passed_time":41.06545153,"remaining_time":94.12945064,"test":[0.7479204715]},
{"learn":[0.7708744661],"iteration":243,"passed_time":41.23508503,"remaining_time":93.96191506,"test":[0.7478352444]},
{"learn":[0.7707021957],"iteration":244,"passed_time":41.4031747,"remaining_time":93.79086513,"test":[0.7476382004]},
{"learn":[0.7706478903],"iteration":245,"passed_time":41.56984787,"remaining_time":93.61664927,"test":[0.7476240215]},
{"learn":[0.7705970506],"iteration":246,"passed_time":41.7387807,"remaining_time":93.44755354,"test":[0.7476263519]},
{"learn":[0.7704253544],"iteration":247,"passed_time":41.90824207,"remaining_time":93.27963558,"test":[0.7475395599]},
{"learn":[0.7703496677],"iteration":248,"passed_time":42.07736779,"remaining_time":93.11096246,"test":[0.747436351]},
{"learn":[0.7702394169],"iteration":249,"passed_time":42.24707456,"remaining_time":92.94356403,"test":[0.7474009916]},
{"learn":[0.7701359172],"iteration":250,"passed_time":42.41768887,"remaining_time":92.77813223,"test":[0.7473456632]},
{"learn":[0.7700903066],"iteration":251,"passed_time":42.58721144,"remaining_time":92.6102852,"test":[0.7473532006]},
{"learn":[0.7699504206],"iteration":252,"passed_time":42.75788102,"remaining_time":92.44490482,"test":[0.7472840963]},
{"learn":[0.7697788905],"iteration":253,"passed_time":42.92393628,"remaining_time":92.26956381,"test":[0.747213963]},
{"learn":[0.7697126417],"iteration":254,"passed_time":43.08768914,"remaining_time":92.08937482,"test":[0.7472148005]},
{"learn":[0.7696149377],"iteration":255,"passed_time":43.25624015,"remaining_time":91.91951033,"test":[0.7471068948]},
{"learn":[0.7694939812],"iteration":256,"passed_time":43.43137512,"remaining_time":91.76356688,"test":[0.7470576183]},
{"learn":[0.7692985998],"iteration":257,"passed_time":43.60635599,"remaining_time":91.60715096,"test":[0.7469220169]},
{"learn":[0.7692118055],"iteration":258,"passed_time":43.77432664,"remaining_time":91.4359487,"test":[0.7468740604]},
{"learn":[0.768971108],"iteration":259,"passed_time":43.94812851,"remaining_time":91.27688229,"test":[0.7466767681]},
{"learn":[0.7688831899],"iteration":260,"passed_time":44.12380812,"remaining_time":91.12158076,"test":[0.746627222]},
{"learn":[0.7687812616],"iteration":261,"passed_time":44.2954537,"remaining_time":90.95784004,"test":[0.7465904719]},
{"learn":[0.7686877408],"iteration":262,"passed_time":44.46235691,"remaining_time":90.78435613,"test":[0.7465199789]},
{"learn":[0.7685989008],"iteration":263,"passed_time":44.63229566,"remaining_time":90.61708513,"test":[0.7464621679]},
{"learn":[0.7684695319],"iteration":264,"passed_time":44.79686767,"remaining_time":90.43895925,"test":[0.7464099091]},
{"learn":[0.7683628082],"iteration":265,"passed_time":44.96748231,"remaining_time":90.27306599,"test":[0.7463862538]},
{"learn":[0.7682251393],"iteration":266,"passed_time":45.13677675,"remaining_time":90.10450191,"test":[0.746318566]},
{"learn":[0.768113884],"iteration":267,"passed_time":45.30791244,"remaining_time":89.93958738,"test":[0.7462850374]},
{"learn":[0.7679614755],"iteration":268,"passed_time":45.47219273,"remaining_time":89.7610942,"test":[0.7462491734]},
{"learn":[0.7678289371],"iteration":269,"passed_time":45.64306972,"remaining_time":89.59565538,"test":[0.7461429585]},
{"learn":[0.767762958],"iteration":270,"passed_time":45.81505973,"remaining_time":89.43234908,"test":[0.7461296309]},
{"learn":[0.7676627571],"iteration":271,"passed_time":45.98364504,"remaining_time":89.26236978,"test":[0.746050661]},
{"learn":[0.7674902291],"iteration":272,"passed_time":46.15506486,"remaining_time":89.09787246,"test":[0.745937461]},
{"learn":[0.7672936013],"iteration":273,"passed_time":46.24644781,"remaining_time":88.77967718,"test":[0.7458012913]},
{"learn":[0.7671630054],"iteration":274,"passed_time":46.40105896,"remaining_time":88.58383983,"test":[0.7457197298]},
{"learn":[0.7671083786],"iteration":275,"passed_time":46.57904722,"remaining_time":88.43268386,"test":[0.7457176687]},
{"learn":[0.7669868401],"iteration":276,"passed_time":46.74864799,"remaining_time":88.26549782,"test":[0.7456488677]},
{"learn":[0.7669151752],"iteration":277,"passed_time":46.92038261,"remaining_time":88.10230115,"test":[0.7455978195]},
{"learn":[0.7668189411],"iteration":278,"passed_time":47.08974226,"remaining_time":87.93460831,"test":[0.7455348745]},
{"learn":[0.7666102471],"iteration":279,"passed_time":47.25224497,"remaining_time":87.75416923,"test":[0.7454334097]},
{"learn":[0.7665289871],"iteration":280,"passed_time":47.42073721,"remaining_time":87.58492034,"test":[0.7453507928]},
{"learn":[0.7664020975],"iteration":281,"passed_time":47.58741048,"remaining_time":87.41233556,"test":[0.7452211405]},
{"learn":[0.7662307166],"iteration":282,"passed_time":47.75698879,"remaining_time":87.24509967,"test":[0.7450784639]},
{"learn":[0.7660674116],"iteration":283,"passed_time":47.9224,"remaining_time":87.07027606,"test":[0.7450134914]},
{"learn":[0.765979822],"iteration":284,"passed_time":48.09178237,"remaining_time":86.90269445,"test":[0.7450097381]},
{"learn":[0.7658692429],"iteration":285,"passed_time":48.26180414,"remaining_time":86.7362494,"test":[0.7449288013]},
{"learn":[0.7656610752],"iteration":286,"passed_time":48.42910547,"remaining_time":86.56491674,"test":[0.7448291429]},
{"learn":[0.765574605],"iteration":287,"passed_time":48.60163342,"remaining_time":86.40290385,"test":[0.7447378224]},
{"learn":[0.7654280457],"iteration":288,"passed_time":48.77101972,"remaining_time":86.23526325,"test":[0.7447105956]},
{"learn":[0.7653086238],"iteration":289,"passed_time":48.94201477,"remaining_time":86.07043976,"test":[0.7446556569]},
{"learn":[0.7652631902],"iteration":290,"passed_time":49.10871659,"remaining_time":85.89806442,"test":[0.7446709256]},
{"learn":[0.7647099167],"iteration":291,"passed_time":49.28423213,"remaining_time":85.74106138,"test":[0.7444807019]},
{"learn":[0.7646299743],"iteration":292,"passed_time":49.45258857,"remaining_time":85.57154405,"test":[0.7444839379]},
{"learn":[0.7643624417],"iteration":293,"passed_time":49.6212539,"remaining_time":85.40256624,"test":[0.7442784771]},
{"learn":[0.764173568],"iteration":294,"passed_time":49.79032959,"remaining_time":85.23429303,"test":[0.7441792638]},
{"learn":[0.7640275641],"iteration":295,"passed_time":49.95915058,"remaining_time":85.06558072,"test":[0.7440752727]},
{"learn":[0.7639388741],"iteration":296,"passed_time":50.12752187,"remaining_time":84.89610606,"test":[0.7439928593]},
{"learn":[0.7637632089],"iteration":297,"passed_time":50.29622997,"remaining_time":84.72720619,"test":[0.7438691241]},
{"learn":[0.7635950963],"iteration":298,"passed_time":50.46560656,"remaining_time":84.55942771,"test":[0.7437538472]},
{"learn":[0.7634439365],"iteration":299,"passed_time":50.63437996,"remaining_time":84.39063327,"test":[0.7436206576]},
{"learn":[0.763205161],"iteration":300,"passed_time":50.79880775,"remaining_time":84.21463477,"test":[0.7435130306]},
{"learn":[0.7631470992],"iteration":301,"passed_time":50.97087723,"remaining_time":84.05131411,"test":[0.7435149422]},
{"learn":[0.7629579906],"iteration":302,"passed_time":51.14230973,"remaining_time":83.88689088,"test":[0.743362531]},
{"learn":[0.7627952333],"iteration":303,"passed_time":51.31386982,"remaining_time":83.72262971,"test":[0.7432653813]},
{"learn":[0.7625601817],"iteration":304,"passed_time":51.48196594,"remaining_time":83.55269882,"test":[0.7431001578]},
{"learn":[0.7625358436],"iteration":305,"passed_time":51.55185612,"remaining_time":83.2242383,"test":[0.743083392]},
{"learn":[0.7624024932],"iteration":306,"passed_time":51.70991018,"remaining_time":83.03904143,"test":[0.7429552469]},
{"learn":[0.7623233463],"iteration":307,"passed_time":51.88735597,"remaining_time":82.88499719,"test":[0.7429266529]},
{"learn":[0.7622221245],"iteration":308,"passed_time":52.06151417,"remaining_time":82.72557753,"test":[0.7428536261]},
{"learn":[0.7620490628],"iteration":309,"passed_time":52.23456406,"remaining_time":82.56431094,"test":[0.7427245038]},
{"learn":[0.7618206504],"iteration":310,"passed_time":52.40682951,"remaining_time":82.40173515,"test":[0.7425641985]},
{"learn":[0.7616955948],"iteration":311,"passed_time":52.5755427,"remaining_time":82.23354114,"test":[0.742481298]},
{"learn":[0.761612406],"iteration":312,"passed_time":52.7457815,"remaining_time":82.06771754,"test":[0.7424636039]},
{"learn":[0.7614551546],"iteration":313,"passed_time":52.91653465,"remaining_time":81.90266191,"test":[0.7423726933]},
{"learn":[0.7613064592],"iteration":314,"passed_time":53.08628546,"remaining_time":81.73602682,"test":[0.742293129]},
{"learn":[0.7611903884],"iteration":315,"passed_time":53.25909549,"remaining_time":81.57405764,"test":[0.742232852]},
{"learn":[0.7610659238],"iteration":316,"passed_time":53.42493112,"remaining_time":81.40139348,"test":[0.7422119411]},
{"learn":[0.7609171833],"iteration":317,"passed_time":53.59683845,"remaining_time":81.23797526,"test":[0.7421089864]},
{"learn":[0.7608018699],"iteration":318,"passed_time":53.76748213,"remaining_time":81.07259844,"test":[0.7420462524]},
{"learn":[0.7607203077],"iteration":319,"passed_time":53.93745933,"remaining_time":80.90618899,"test":[0.7419729318]},
{"learn":[0.7606500092],"iteration":320,"passed_time":54.10438429,"remaining_time":80.73520272,"test":[0.7419958279]},
{"learn":[0.7605755788],"iteration":321,"passed_time":54.26603746,"remaining_time":80.55641585,"test":[0.74199811]},
{"learn":[0.7604235598],"iteration":322,"passed_time":54.4355802,"remaining_time":80.38938623,"test":[0.7418771073]},
{"learn":[0.7603116742],"iteration":323,"passed_time":54.60645269,"remaining_time":80.22429469,"test":[0.7418345258]},
{"learn":[0.760199463],"iteration":324,"passed_time":54.77570964,"remaining_time":80.05680639,"test":[0.7417568611]},
{"learn":[0.7599751449],"iteration":325,"passed_time":54.94594873,"remaining_time":79.89073527,"test":[0.7417239212]},
{"learn":[0.7598450774],"iteration":326,"passed_time":55.11727696,"remaining_time":79.72621408,"test":[0.7416551628]},
{"learn":[0.7594505611],"iteration":327,"passed_time":55.28888105,"remaining_time":79.56204834,"test":[0.7414269173]},
{"learn":[0.7590656248],"iteration":328,"passed_time":55.45785414,"remaining_time":79.39407083,"test":[0.7411954354]},
{"learn":[0.7589748179],"iteration":329,"passed_time":55.62648483,"remaining_time":79.2255996,"test":[0.7410950642]},
{"learn":[0.7588095034],"iteration":330,"passed_time":55.7982599,"remaining_time":79.06158275,"test":[0.7410355742]},
{"learn":[0.7586098909],"iteration":331,"passed_time":55.9689132,"remaining_time":78.89593789,"test":[0.7410006293]},
{"learn":[0.7585168248],"iteration":332,"passed_time":56.14454255,"remaining_time":78.73724135,"test":[0.7409760052]},
{"learn":[0.7583609454],"iteration":333,"passed_time":56.31528897,"remaining_time":78.57163072,"test":[0.7409132176]},
{"learn":[0.7582955006],"iteration":334,"passed_time":56.49188697,"remaining_time":78.41411177,"test":[0.7408954638]},
{"learn":[0.7581620285],"iteration":335,"passed_time":56.66716368,"remaining_time":78.25465461,"test":[0.7408300425]},
{"learn":[0.7580078203],"iteration":336,"passed_time":56.83748632,"remaining_time":78.08829723,"test":[0.7407152656]},
{"learn":[0.7578965086],"iteration":337,"passed_time":57.00852428,"remaining_time":77.92289414,"test":[0.7406810039]},
{"learn":[0.7577968104],"iteration":338,"passed_time":57.18832796,"remaining_time":77.76937814,"test":[0.7406453647]},
{"learn":[0.7576392066],"iteration":339,"passed_time":57.36271783,"remaining_time":77.60838294,"test":[0.7406024906]},
{"learn":[0.7575024163],"iteration":340,"passed_time":57.52780298,"remaining_time":77.43478466,"test":[0.7404995917]},
{"learn":[0.7574008407],"iteration":341,"passed_time":57.70285358,"remaining_time":77.27458169,"test":[0.7404203949]},
{"learn":[0.7572087998],"iteration":342,"passed_time":57.87310931,"remaining_time":77.10790366,"test":[0.7403718763]},
{"learn":[0.7570745721],"iteration":343,"passed_time":58.04116902,"remaining_time":76.93829381,"test":[0.7403229489]},
{"learn":[0.7567334689],"iteration":344,"passed_time":58.21466649,"remaining_time":76.77586451,"test":[0.740156273]},
{"learn":[0.756539244],"iteration":345,"passed_time":58.38564967,"remaining_time":76.61007211,"test":[0.7400862921]},
{"learn":[0.7562942395],"iteration":346,"passed_time":58.5556796,"remaining_time":76.44300535,"test":[0.7398831014]},
{"learn":[0.7560880553],"iteration":347,"passed_time":58.72534123,"remaining_time":76.27544321,"test":[0.7397333126]},
{"learn":[0.7559677758],"iteration":348,"passed_time":58.89320761,"remaining_time":76.10554909,"test":[0.7397179196]},
{"learn":[0.7558808978],"iteration":349,"passed_time":59.0603638,"remaining_time":75.93475346,"test":[0.7396683862]},
{"learn":[0.7557646273],"iteration":350,"passed_time":59.22768497,"remaining_time":75.7641896,"test":[0.739610865]},
{"learn":[0.7556479838],"iteration":351,"passed_time":59.39621836,"remaining_time":75.59518701,"test":[0.7395944853]},
{"learn":[0.7554697992],"iteration":352,"passed_time":59.56693255,"remaining_time":75.42894858,"test":[0.7394703879]},
{"learn":[0.7553244269],"iteration":353,"passed_time":59.73702423,"remaining_time":75.26190059,"test":[0.7393810052]},
{"learn":[0.7551818668],"iteration":354,"passed_time":59.9134852,"remaining_time":75.10281948,"test":[0.7393617742]},
{"learn":[0.7547839155],"iteration":355,"passed_time":60.09216726,"remaining_time":74.94641085,"test":[0.7391026387]},
{"learn":[0.7546113353],"iteration":356,"passed_time":60.26056139,"remaining_time":74.7771112,"test":[0.7389682835]},
{"learn":[0.7544204762],"iteration":357,"passed_time":60.43639474,"remaining_time":74.61700133,"test":[0.7388098291]},
{"learn":[0.7542732665],"iteration":358,"passed_time":60.61037704,"remaining_time":74.45453001,"test":[0.7387193198]},
{"learn":[0.7541022542],"iteration":359,"passed_time":60.77905731,"remaining_time":74.28551449,"test":[0.7386266268]},
{"learn":[0.7539529634],"iteration":360,"passed_time":60.95459126,"remaining_time":74.12483536,"test":[0.7385392875]},
{"learn":[0.7537831871],"iteration":361,"passed_time":61.1226414,"remaining_time":73.95501915,"test":[0.7384717415]},
{"learn":[0.753672158],"iteration":362,"passed_time":61.28753935,"remaining_time":73.78141789,"test":[0.7384171422]},
{"learn":[0.7535428559],"iteration":363,"passed_time":61.45705356,"remaining_time":73.61339383,"test":[0.7383260573]},
{"learn":[0.7534583695],"iteration":364,"passed_time":61.63395761,"remaining_time":73.45416866,"test":[0.7382700116]},
{"learn":[0.7533026359],"iteration":365,"passed_time":61.80194292,"remaining_time":73.28427111,"test":[0.7382106604]},
{"learn":[0.7532413539],"iteration":366,"passed_time":61.96584526,"remaining_time":73.10956675,"test":[0.7381611036]},
{"learn":[0.7530832279],"iteration":367,"passed_time":62.13587282,"remaining_time":72.94211157,"test":[0.7381718939]},
{"learn":[0.753012425],"iteration":368,"passed_time":62.30427062,"remaining_time":72.77273885,"test":[0.7381296565]},
{"learn":[0.7526631575],"iteration":369,"passed_time":62.48082967,"remaining_time":72.61285611,"test":[0.738042847]},
{"learn":[0.7523397243],"iteration":370,"passed_time":62.65130761,"remaining_time":72.44585166,"test":[0.7378960089]},
{"learn":[0.7521982676],"iteration":371,"passed_time":62.82232624,"remaining_time":72.27945062,"test":[0.7378415485]},
{"learn":[0.7519659161],"iteration":372,"passed_time":62.99062037,"remaining_time":72.1099059,"test":[0.7376843851]},
{"learn":[0.7518266613],"iteration":373,"passed_time":63.16122058,"remaining_time":71.94299457,"test":[0.7377123768]},
{"learn":[0.7517537991],"iteration":374,"passed_time":63.32959412,"remaining_time":71.77354,"test":[0.7377078084]},
{"learn":[0.7516350325],"iteration":375,"passed_time":63.49678143,"remaining_time":71.60275353,"test":[0.7377381018]},
{"learn":[0.7514877638],"iteration":376,"passed_time":63.66851003,"remaining_time":71.43708154,"test":[0.7377458379]},
{"learn":[0.7513374526],"iteration":377,"passed_time":63.83776962,"remaining_time":71.26862111,"test":[0.7377216683]},
{"learn":[0.7510935961],"iteration":378,"passed_time":64.00453395,"remaining_time":71.09738467,"test":[0.7376325418]},
{"learn":[0.7509610631],"iteration":379,"passed_time":64.16971213,"remaining_time":70.92441867,"test":[0.7375594278]},
{"learn":[0.7508396142],"iteration":380,"passed_time":64.33986996,"remaining_time":70.75696985,"test":[0.737507457]},
{"learn":[0.7507372378],"iteration":381,"passed_time":64.50594289,"remaining_time":70.58503699,"test":[0.7375065129]},
{"learn":[0.7506459545],"iteration":382,"passed_time":64.67565207,"remaining_time":70.41709377,"test":[0.7374425922]},
{"learn":[0.7503812773],"iteration":383,"passed_time":64.84890204,"remaining_time":70.25297721,"test":[0.7372967632]},
{"learn":[0.7502892033],"iteration":384,"passed_time":65.01454734,"remaining_time":70.08061597,"test":[0.7372446444]},
{"learn":[0.7501351785],"iteration":385,"passed_time":65.18144608,"remaining_time":69.90963387,"test":[0.7371352679]},
{"learn":[0.750018651],"iteration":386,"passed_time":65.349202,"remaining_time":69.73958766,"test":[0.7370916693]},
{"learn":[0.7498317714],"iteration":387,"passed_time":65.52595415,"remaining_time":69.57910595,"test":[0.7369618351]},
{"learn":[0.749727103],"iteration":388,"passed_time":65.69922707,"remaining_time":69.41486459,"test":[0.7369009772]},
{"learn":[0.7496278889],"iteration":389,"passed_time":65.87007943,"remaining_time":69.24803223,"test":[0.7368288329]},
{"learn":[0.74940717],"iteration":390,"passed_time":66.04508087,"remaining_time":69.08551937,"test":[0.7367458053]},
{"learn":[0.7492455787],"iteration":391,"passed_time":66.21475941,"remaining_time":68.91740265,"test":[0.7366582893]},
{"learn":[0.7491643543],"iteration":392,"passed_time":66.38181331,"remaining_time":68.74655984,"test":[0.7366045514]},
{"learn":[0.7490533382],"iteration":393,"passed_time":66.54654878,"remaining_time":68.57334722,"test":[0.7365572252]},
{"learn":[0.7489272057],"iteration":394,"passed_time":66.71500011,"remaining_time":68.40398745,"test":[0.7364834741]},
{"learn":[0.7488364701],"iteration":395,"passed_time":66.88457008,"remaining_time":68.23577352,"test":[0.736466381]},
{"learn":[0.7487287731],"iteration":396,"passed_time":67.05798738,"remaining_time":68.07145823,"test":[0.736395723]},
{"learn":[0.74861115],"iteration":397,"passed_time":67.22497099,"remaining_time":67.90059884,"test":[0.736384315]},
{"learn":[0.7485480368],"iteration":398,"passed_time":67.39111933,"remaining_time":67.72891943,"test":[0.7363733718]},
{"learn":[0.7483055262],"iteration":399,"passed_time":67.56557369,"remaining_time":67.56557369,"test":[0.7362854093]},
{"learn":[0.748203428],"iteration":400,"passed_time":67.73969647,"remaining_time":67.40184263,"test":[0.7362580358]},
{"learn":[0.7481258444],"iteration":401,"passed_time":67.90688953,"remaining_time":67.23119908,"test":[0.7362370992]},
{"learn":[0.7479482856],"iteration":402,"passed_time":68.07836594,"remaining_time":67.06479226,"test":[0.7361828269]},
{"learn":[0.7478415583],"iteration":403,"passed_time":68.24568574,"remaining_time":66.89428602,"test":[0.7361297606]},
{"learn":[0.7477081521],"iteration":404,"passed_time":68.41568763,"remaining_time":66.72641139,"test":[0.7359994314]},
{"learn":[0.7476160355],"iteration":405,"passed_time":68.58513835,"remaining_time":66.5579914,"test":[0.7359778912]},
{"learn":[0.7473833019],"iteration":406,"passed_time":68.75326262,"remaining_time":66.38828553,"test":[0.7358644803]},
{"learn":[0.7472975501],"iteration":407,"passed_time":68.92113623,"remaining_time":66.21834657,"test":[0.7358655543]},
{"learn":[0.74721149],"iteration":408,"passed_time":69.08900128,"remaining_time":66.04840954,"test":[0.7358455737]},
{"learn":[0.7471263344],"iteration":409,"passed_time":69.2618366,"remaining_time":65.88321043,"test":[0.7358740319]},
{"learn":[0.7469599608],"iteration":410,"passed_time":69.42417819,"remaining_time":65.70804213,"test":[0.7357853514]},
{"learn":[0.7467534528],"iteration":411,"passed_time":69.59145559,"remaining_time":65.53758439,"test":[0.7357274233]},
{"learn":[0.7466681385],"iteration":412,"passed_time":69.76636095,"remaining_time":65.37428981,"test":[0.7356865637]},
{"learn":[0.7464223287],"iteration":413,"passed_time":69.93694417,"remaining_time":65.2069093,"test":[0.7356024221]},
{"learn":[0.7463232],"iteration":414,"passed_time":70.10654557,"remaining_time":65.03860251,"test":[0.7355253937]},
{"learn":[0.746239048],"iteration":415,"passed_time":70.27881115,"remaining_time":64.87274876,"test":[0.7355167065]},
{"learn":[0.7460463238],"iteration":416,"passed_time":70.44842337,"remaining_time":64.70442722,"test":[0.7354627323]},
{"learn":[0.7459369398],"iteration":417,"passed_time":70.61844463,"remaining_time":64.53647332,"test":[0.7354268115]},
{"learn":[0.7458116652],"iteration":418,"passed_time":70.78751626,"remaining_time":64.36764605,"test":[0.7354504405]},
{"learn":[0.7456555087],"iteration":419,"passed_time":70.95711777,"remaining_time":64.19929703,"test":[0.735383085]},
{"learn":[0.7455685916],"iteration":420,"passed_time":71.12715092,"remaining_time":64.03133063,"test":[0.7353653655]},
{"learn":[0.7454820152],"iteration":421,"passed_time":71.30125877,"remaining_time":63.8670043,"test":[0.7353836473]},
{"learn":[0.7453811442],"iteration":422,"passed_time":71.47414471,"remaining_time":63.70154269,"test":[0.7353251945]},
{"learn":[0.7452855645],"iteration":423,"passed_time":71.64454863,"remaining_time":63.53384501,"test":[0.7352702395]},
{"learn":[0.7451688964],"iteration":424,"passed_time":71.81649186,"remaining_time":63.36749282,"test":[0.7352142577]},
{"learn":[0.7450279645],"iteration":425,"passed_time":71.9870757,"remaining_time":63.19992092,"test":[0.7351660547]},
{"learn":[0.7449164683],"iteration":426,"passed_time":72.15961097,"remaining_time":63.03403956,"test":[0.7351113183]},
{"learn":[0.7448508533],"iteration":427,"passed_time":72.33091312,"remaining_time":62.86705533,"test":[0.7351090958]},
{"learn":[0.7447555934],"iteration":428,"passed_time":72.50040096,"remaining_time":62.69848195,"test":[0.7351097806]},
{"learn":[0.7443906379],"iteration":429,"passed_time":72.67673018,"remaining_time":62.53579108,"test":[0.7349811488]},
{"learn":[0.7442548927],"iteration":430,"passed_time":72.84413253,"remaining_time":62.36539421,"test":[0.7349342815]},
{"learn":[0.7440997916],"iteration":431,"passed_time":73.01601534,"remaining_time":62.19882788,"test":[0.7348577958]},
{"learn":[0.7439714756],"iteration":432,"passed_time":73.18331359,"remaining_time":62.02835124,"test":[0.7348228339]},
{"learn":[0.7438211657],"iteration":433,"passed_time":73.35216761,"remaining_time":61.85920126,"test":[0.7347687264]},
{"learn":[0.7436353707],"iteration":434,"passed_time":73.52598649,"remaining_time":61.69421855,"test":[0.7346284405]},
{"learn":[0.7434862091],"iteration":435,"passed_time":73.69850047,"remaining_time":61.5281059,"test":[0.734630993]},
{"learn":[0.7433308986],"iteration":436,"passed_time":73.87023326,"remaining_time":61.36131504,"test":[0.734638587]},
{"learn":[0.7432492024],"iteration":437,"passed_time":74.04339702,"remaining_time":61.1956843,"test":[0.7346601729]},
{"learn":[0.7431840879],"iteration":438,"passed_time":74.21602087,"remaining_time":61.02957525,"test":[0.7346586434]},
{"learn":[0.7429234598],"iteration":439,"passed_time":74.38830096,"remaining_time":60.86315533,"test":[0.7345605187]},
{"learn":[0.7426505855],"iteration":440,"passed_time":74.56184226,"remaining_time":60.69773553,"test":[0.7345221626]},
{"learn":[0.7425572791],"iteration":441,"passed_time":74.7338096,"remaining_time":60.53100416,"test":[0.7345435301]},
{"learn":[0.7423941919],"iteration":442,"passed_time":74.90357582,"remaining_time":60.36247532,"test":[0.7344750396]},
{"learn":[0.7423032882],"iteration":443,"passed_time":75.0794135,"remaining_time":60.19880902,"test":[0.7344123556]},
{"learn":[0.7421856718],"iteration":444,"passed_time":75.25057289,"remaining_time":60.0313559,"test":[0.7343374108]},
{"learn":[0.742038695],"iteration":445,"passed_time":75.42072603,"remaining_time":59.86308748,"test":[0.7342449768]},
{"learn":[0.741932445],"iteration":446,"passed_time":75.59269482,"remaining_time":59.69624446,"test":[0.7342113467]},
{"learn":[0.7418097916],"iteration":447,"passed_time":75.76549345,"remaining_time":59.53003056,"test":[0.7341545115]},
{"learn":[0.7417301263],"iteration":448,"passed_time":75.93433632,"remaining_time":59.36069498,"test":[0.7341061901]},
{"learn":[0.7416144602],"iteration":449,"passed_time":76.10114814,"remaining_time":59.18978188,"test":[0.734045636]},
{"learn":[0.7415402932],"iteration":450,"passed_time":76.27333028,"remaining_time":59.02304272,"test":[0.7340257093]},
{"learn":[0.7414484728],"iteration":451,"passed_time":76.4511642,"remaining_time":58.86063084,"test":[0.7339857774]},
{"learn":[0.7413522111],"iteration":452,"passed_time":76.63606173,"remaining_time":58.70356163,"test":[0.7339494162]},
{"learn":[0.7412947999],"iteration":453,"passed_time":76.80837752,"remaining_time":58.53678111,"test":[0.7339272877]},
{"learn":[0.7412011236],"iteration":454,"passed_time":76.99285045,"remaining_time":58.3791943,"test":[0.7338766298]},
{"learn":[0.7410854637],"iteration":455,"passed_time":77.16222451,"remaining_time":58.21009919,"test":[0.7338703001]},
{"learn":[0.7408967729],"iteration":456,"passed_time":77.34384527,"remaining_time":58.05019459,"test":[0.7337967229]},
{"learn":[0.7408291878],"iteration":457,"passed_time":77.51910542,"remaining_time":57.88544553,"test":[0.7337873923]},
{"learn":[0.7405868316],"iteration":458,"passed_time":77.68953086,"remaining_time":57.71705887,"test":[0.7337305834]},
{"learn":[0.7404724902],"iteration":459,"passed_time":77.85895687,"remaining_time":57.54792464,"test":[0.7336645575]},
{"learn":[0.7403187505],"iteration":460,"passed_time":78.03388496,"remaining_time":57.38283515,"test":[0.733627937]},
{"learn":[0.7401364543],"iteration":461,"passed_time":78.23486995,"remaining_time":57.23676633,"test":[0.7335716823]},
{"learn":[0.7400508838],"iteration":462,"passed_time":78.41198931,"remaining_time":57.07308941,"test":[0.733529313]},
{"learn":[0.7397843891],"iteration":463,"passed_time":78.5866767,"remaining_time":56.90759347,"test":[0.733440516]},
{"learn":[0.7397342972],"iteration":464,"passed_time":78.75759823,"remaining_time":56.73934496,"test":[0.7334266315]},
{"learn":[0.7396328436],"iteration":465,"passed_time":78.93300498,"remaining_time":56.57429971,"test":[0.7334324357]},
{"learn":[0.7395506131],"iteration":466,"passed_time":79.10090845,"remaining_time":56.40385978,"test":[0.7333982454]},
{"learn":[0.7394177968],"iteration":467,"passed_time":79.27655341,"remaining_time":56.23892251,"test":[0.7333268552]},
{"learn":[0.739325615],"iteration":468,"passed_time":79.44267117,"remaining_time":56.06721569,"test":[0.7333017349]},
{"learn":[0.7392357398],"iteration":469,"passed_time":79.6082782,"remaining_time":55.89517405,"test":[0.7332638022]},
{"learn":[0.7391192153],"iteration":470,"passed_time":79.78114449,"remaining_time":55.72823044,"test":[0.733251365]},
{"learn":[0.738967733],"iteration":471,"passed_time":79.94774089,"remaining_time":55.55690469,"test":[0.7331794842]},
{"learn":[0.7388315],"iteration":472,"passed_time":80.11257513,"remaining_time":55.38438069,"test":[0.7331295824]},
{"learn":[0.7387570258],"iteration":473,"passed_time":80.28206714,"remaining_time":55.21509259,"test":[0.7330883219]},
{"learn":[0.7386824077],"iteration":474,"passed_time":80.46316034,"remaining_time":55.05374128,"test":[0.7330609238]},
{"learn":[0.7385700639],"iteration":475,"passed_time":80.64030127,"remaining_time":54.88961683,"test":[0.7329930702]},
{"learn":[0.7385189373],"iteration":476,"passed_time":80.82277445,"remaining_time":54.72904853,"test":[0.7329760301]},
{"learn":[0.7384421481],"iteration":477,"passed_time":80.99348274,"remaining_time":54.56046327,"test":[0.7329542155]},
{"learn":[0.7383534234],"iteration":478,"passed_time":81.16457333,"remaining_time":54.39212534,"test":[0.732945464]},
{"learn":[0.7381774515],"iteration":479,"passed_time":81.34356404,"remaining_time":54.2290427,"test":[0.7328665498]},
{"learn":[0.7380968661],"iteration":480,"passed_time":81.52452695,"remaining_time":54.06720186,"test":[0.7328556696]},
{"learn":[0.7380238304],"iteration":481,"passed_time":81.69249641,"remaining_time":53.89670925,"test":[0.7328395811]},
{"learn":[0.73785285],"iteration":482,"passed_time":81.86451848,"remaining_time":53.72888687,"test":[0.7327639337]},
{"learn":[0.7377290337],"iteration":483,"passed_time":82.03809321,"remaining_time":53.56206086,"test":[0.7327714534]},
{"learn":[0.7376609118],"iteration":484,"passed_time":82.20886256,"remaining_time":53.39338496,"test":[0.7327734931]},
{"learn":[0.7375867997],"iteration":485,"passed_time":82.37584435,"remaining_time":53.22225334,"test":[0.7327737854]},
{"learn":[0.7375251772],"iteration":486,"passed_time":82.54467161,"remaining_time":53.05232488,"test":[0.7327578268]},
{"learn":[0.7374503433],"iteration":487,"passed_time":82.7169469,"remaining_time":52.8846054,"test":[0.7327736352]},
{"learn":[0.7373952506],"iteration":488,"passed_time":82.8891311,"remaining_time":52.71680935,"test":[0.7327710605]},
{"learn":[0.7373081686],"iteration":489,"passed_time":83.06269325,"remaining_time":52.54986716,"test":[0.7327226074]},
{"learn":[0.7372320802],"iteration":490,"passed_time":83.23288164,"remaining_time":52.3807748,"test":[0.7326622027]},
{"learn":[0.7371707623],"iteration":491,"passed_time":83.40506858,"remaining_time":52.21292911,"test":[0.7326368843]},
{"learn":[0.7370527674],"iteration":492,"passed_time":83.57517936,"remaining_time":52.04377295,"test":[0.7325570756]},
{"learn":[0.7369813674],"iteration":493,"passed_time":83.74198298,"remaining_time":51.87256435,"test":[0.7325624349]},
{"learn":[0.7369167659],"iteration":494,"passed_time":83.91386398,"remaining_time":51.70450205,"test":[0.7325242851]},
{"learn":[0.736641709],"iteration":495,"passed_time":84.0852788,"remaining_time":51.53613862,"test":[0.7324817033]},
{"learn":[0.7365536928],"iteration":496,"passed_time":84.25921637,"remaining_time":51.36930093,"test":[0.7324491868]},
{"learn":[0.7364409902],"iteration":497,"passed_time":84.43574552,"remaining_time":51.20400632,"test":[0.7324201994]},
{"learn":[0.7363824308],"iteration":498,"passed_time":84.6108537,"remaining_time":51.03780954,"test":[0.7323988145]},
{"learn":[0.7362666531],"iteration":499,"passed_time":84.78504234,"remaining_time":50.8710254,"test":[0.7323044193]},
{"learn":[0.736112405],"iteration":500,"passed_time":84.95448242,"remaining_time":50.70137773,"test":[0.7323015066]},
{"learn":[0.7360378157],"iteration":501,"passed_time":85.13123354,"remaining_time":50.53607091,"test":[0.7322930594]},
{"learn":[0.735997594],"iteration":502,"passed_time":85.30665622,"remaining_time":50.36993419,"test":[0.7322959455]},
{"learn":[0.735902988],"iteration":503,"passed_time":85.47485819,"remaining_time":50.19951989,"test":[0.7322809571]},
{"learn":[0.7358088586],"iteration":504,"passed_time":85.64411392,"remaining_time":50.02972992,"test":[0.7322703777]},
{"learn":[0.7357500939],"iteration":505,"passed_time":85.81636884,"remaining_time":49.86168466,"test":[0.7322628974]},
{"learn":[0.735617452],"iteration":506,"passed_time":85.99060054,"remaining_time":49.6947652,"test":[0.7322287193]},
{"learn":[0.7355521362],"iteration":507,"passed_time":86.16236316,"remaining_time":49.52639772,"test":[0.7322120402]},
{"learn":[0.7354808005],"iteration":508,"passed_time":86.33190036,"remaining_time":49.35674461,"test":[0.7321744254]},
{"learn":[0.7354453732],"iteration":509,"passed_time":86.50226925,"remaining_time":49.18756487,"test":[0.7321816563]},
{"learn":[0.735380484],"iteration":510,"passed_time":86.67096683,"remaining_time":49.01743525,"test":[0.7321479497]},
{"learn":[0.7351869241],"iteration":511,"passed_time":86.84251565,"remaining_time":48.84891505,"test":[0.7321166442]},
{"learn":[0.7350058187],"iteration":512,"passed_time":87.00596004,"remaining_time":48.67584899,"test":[0.7320319659]},
{"learn":[0.7349375366],"iteration":513,"passed_time":87.18014028,"remaining_time":48.50879401,"test":[0.7320251939]},
{"learn":[0.7347951211],"iteration":514,"passed_time":87.34814679,"remaining_time":48.33829482,"test":[0.7319671435]},
{"learn":[0.7346030273],"iteration":515,"passed_time":87.51470034,"remaining_time":48.16700561,"test":[0.7318761189]},
{"learn":[0.7344528987],"iteration":516,"passed_time":87.68581619,"remaining_time":47.99823207,"test":[0.7318369698]},
{"learn":[0.7343688319],"iteration":517,"passed_time":87.85331508,"remaining_time":47.82748041,"test":[0.7318128113]},
{"learn":[0.7343005912],"iteration":518,"passed_time":88.02451207,"remaining_time":47.65874353,"test":[0.73181802]},
{"learn":[0.7342349358],"iteration":519,"passed_time":88.19658071,"remaining_time":47.49046654,"test":[0.7317828152]},
{"learn":[0.7341662442],"iteration":520,"passed_time":88.36823535,"remaining_time":47.32195329,"test":[0.7317561145]},
{"learn":[0.7340733475],"iteration":521,"passed_time":88.53918535,"remaining_time":47.15305273,"test":[0.7317156199]},
{"learn":[0.7339997998],"iteration":522,"passed_time":88.70685754,"remaining_time":46.9824083,"test":[0.7316560967]},
{"learn":[0.733887292],"iteration":523,"passed_time":88.87380979,"remaining_time":46.811396,"test":[0.7316326738]},
{"learn":[0.7337817787],"iteration":524,"passed_time":89.0411556,"remaining_time":46.64060532,"test":[0.731615227]},
{"learn":[0.7337265073],"iteration":525,"passed_time":89.2136053,"remaining_time":46.47248641,"test":[0.731621731]},
{"learn":[0.7335430198],"iteration":526,"passed_time":89.38400427,"remaining_time":46.30328874,"test":[0.7316046281]},
{"learn":[0.7333932435],"iteration":527,"passed_time":89.55064268,"remaining_time":46.13214926,"test":[0.7315838107]},
{"learn":[0.7333211207],"iteration":528,"passed_time":89.71859888,"remaining_time":45.96170188,"test":[0.7315406958]},
{"learn":[0.7331144538],"iteration":529,"passed_time":89.89091073,"remaining_time":45.79348282,"test":[0.7314687623]},
{"learn":[0.733057222],"iteration":530,"passed_time":90.05976151,"remaining_time":45.623495,"test":[0.7314198977]},
{"learn":[0.7328650119],"iteration":531,"passed_time":90.22852871,"remaining_time":45.45346935,"test":[0.7313123056]},
{"learn":[0.7327611501],"iteration":532,"passed_time":90.3984556,"remaining_time":45.28402936,"test":[0.7313043197]},
{"learn":[0.73251917],"iteration":533,"passed_time":90.57229949,"remaining_time":45.1165387,"test":[0.7312335642]},
{"learn":[0.732435775],"iteration":534,"passed_time":90.74313447,"remaining_time":44.9475339,"test":[0.7312221532]},
{"learn":[0.7323405797],"iteration":535,"passed_time":90.91538942,"remaining_time":44.77922166,"test":[0.7312026468]},
{"learn":[0.7321851408],"iteration":536,"passed_time":91.08979761,"remaining_time":44.61194929,"test":[0.7311908089]},
{"learn":[0.7321054828],"iteration":537,"passed_time":91.26023144,"remaining_time":44.44271494,"test":[0.7311809782]},
{"learn":[0.7319686862],"iteration":538,"passed_time":91.42991185,"remaining_time":44.2731113,"test":[0.7312183729]},
{"learn":[0.7318287905],"iteration":539,"passed_time":91.6042151,"remaining_time":44.10573319,"test":[0.7311512539]},
{"learn":[0.7317353892],"iteration":540,"passed_time":91.77530161,"remaining_time":43.9367895,"test":[0.7311218972]},
{"learn":[0.7316003785],"iteration":541,"passed_time":91.94964714,"remaining_time":43.76938923,"test":[0.7310535008]},
{"learn":[0.7314894225],"iteration":542,"passed_time":92.11646931,"remaining_time":43.5984026,"test":[0.7310059893]},
{"learn":[0.7313931574],"iteration":543,"passed_time":92.28415865,"remaining_time":43.42783936,"test":[0.7309551891]},
{"learn":[0.7311878316],"iteration":544,"passed_time":92.4549635,"remaining_time":43.25874439,"test":[0.7308795227]},
{"learn":[0.7311004752],"iteration":545,"passed_time":92.62136167,"remaining_time":43.08759316,"test":[0.7308481372]},
{"learn":[0.7309829893],"iteration":546,"passed_time":92.79662259,"remaining_time":42.92055853,"test":[0.7307815634]},
{"learn":[0.7309346283],"iteration":547,"passed_time":92.96794286,"remaining_time":42.75168175,"test":[0.7307991898]},
{"learn":[0.7308299763],"iteration":548,"passed_time":93.13773828,"remaining_time":42.58209892,"test":[0.7307914676]},
{"learn":[0.7307149155],"iteration":549,"passed_time":93.31638985,"remaining_time":42.41654084,"test":[0.7307710516]},
{"learn":[0.7306505992],"iteration":550,"passed_time":93.48459293,"remaining_time":42.2462135,"test":[0.7307438548]},
{"learn":[0.7305500448],"iteration":551,"passed_time":93.6505398,"remaining_time":42.0748802,"test":[0.7307135402]},
{"learn":[0.7304868221],"iteration":552,"passed_time":93.8120727,"remaining_time":41.90159486,"test":[0.7306576624]},
{"learn":[0.7304294939],"iteration":553,"passed_time":93.98346429,"remaining_time":41.73272963,"test":[0.7306339982]},
{"learn":[0.730370141],"iteration":554,"passed_time":94.16105304,"remaining_time":41.56659098,"test":[0.7306198716]},
{"learn":[0.7303058118],"iteration":555,"passed_time":94.33603421,"remaining_time":41.39926681,"test":[0.7306310888]},
{"learn":[0.7302077106],"iteration":556,"passed_time":94.50534351,"remaining_time":41.22944071,"test":[0.7306160473]},
{"learn":[0.7300320708],"iteration":557,"passed_time":94.6742036,"remaining_time":41.05942163,"test":[0.7305543583]},
{"learn":[0.7299218003],"iteration":558,"passed_time":94.84482664,"remaining_time":40.89016676,"test":[0.7305330302]},
{"learn":[0.7298657553],"iteration":559,"passed_time":95.01948617,"remaining_time":40.72263693,"test":[0.7304877414]},
{"learn":[0.7296806209],"iteration":560,"passed_time":95.19700051,"remaining_time":40.5562979,"test":[0.7305436688]},
{"learn":[0.7295508826],"iteration":561,"passed_time":95.36314493,"remaining_time":40.38510408,"test":[0.7304359652]},
{"learn":[0.7294821947],"iteration":562,"passed_time":95.53619366,"remaining_time":40.21683463,"test":[0.7304317803]},
{"learn":[0.729397971],"iteration":563,"passed_time":95.70492907,"remaining_time":40.04674337,"test":[0.7304215949]},
{"learn":[0.7292387224],"iteration":564,"passed_time":95.87728117,"remaining_time":39.87816119,"test":[0.7304362482]},
{"learn":[0.7290709467],"iteration":565,"passed_time":96.05089904,"remaining_time":39.710089,"test":[0.7303801094]},
{"learn":[0.7289882239],"iteration":566,"passed_time":96.22150926,"remaining_time":39.5407613,"test":[0.730345989]},
{"learn":[0.728924156],"iteration":567,"passed_time":96.39107426,"remaining_time":39.37100216,"test":[0.7303125743]},
{"learn":[0.7288343951],"iteration":568,"passed_time":96.55927444,"remaining_time":39.20068962,"test":[0.7303217496]},
{"learn":[0.7286460299],"iteration":569,"passed_time":96.72947454,"remaining_time":39.03119148,"test":[0.7303072296]},
{"learn":[0.7285739069],"iteration":570,"passed_time":96.90181255,"remaining_time":38.86254829,"test":[0.7302824772]},
{"learn":[0.7285082759],"iteration":571,"passed_time":97.07089622,"remaining_time":38.69259499,"test":[0.7302720751]},
{"learn":[0.7283996997],"iteration":572,"passed_time":97.24191441,"remaining_time":38.52341112,"test":[0.7302193964]},
{"learn":[0.7283447308],"iteration":573,"passed_time":97.41020775,"remaining_time":38.353148,"test":[0.7301875255]},
{"learn":[0.7282633485],"iteration":574,"passed_time":97.57615829,"remaining_time":38.18197498,"test":[0.7301790617]},
{"learn":[0.7281600111],"iteration":575,"passed_time":97.74445555,"remaining_time":38.01173272,"test":[0.7301149929]},
{"learn":[0.7281173582],"iteration":576,"passed_time":97.91274643,"remaining_time":37.84149472,"test":[0.7301192029]},
{"learn":[0.7279809177],"iteration":577,"passed_time":98.08527834,"remaining_time":37.67289237,"test":[0.7300845514]},
{"learn":[0.7278279728],"iteration":578,"passed_time":98.25411543,"remaining_time":37.50286617,"test":[0.7299941886]},
{"learn":[0.7277700264],"iteration":579,"passed_time":98.42581042,"remaining_time":37.33392809,"test":[0.7299829585]},
{"learn":[0.7275175324],"iteration":580,"passed_time":98.59452407,"remaining_time":37.16385675,"test":[0.7299331699]},
{"learn":[0.7274652158],"iteration":581,"passed_time":98.7695153,"remaining_time":36.99614147,"test":[0.7299406041]},
{"learn":[0.7274045028],"iteration":582,"passed_time":98.94780332,"remaining_time":36.82962834,"test":[0.7299431659]},
{"learn":[0.7272892614],"iteration":583,"passed_time":99.12399705,"remaining_time":36.66230028,"test":[0.729914554]},
{"learn":[0.7272324472],"iteration":584,"passed_time":99.29108782,"remaining_time":36.49159638,"test":[0.7298792388]},
{"learn":[0.7271412283],"iteration":585,"passed_time":99.46025949,"remaining_time":36.32166473,"test":[0.7298480741]},
{"learn":[0.7270257195],"iteration":586,"passed_time":99.62957053,"remaining_time":36.15178624,"test":[0.7297907664]},
{"learn":[0.7269574425],"iteration":587,"passed_time":99.80181115,"remaining_time":35.98296593,"test":[0.7297769114]},
{"learn":[0.7268745355],"iteration":588,"passed_time":99.96934927,"remaining_time":35.8124494,"test":[0.7297884021]},
{"learn":[0.7267543696],"iteration":589,"passed_time":100.143587,"remaining_time":35.64432756,"test":[0.7298429309]},
{"learn":[0.7267067682],"iteration":590,"passed_time":100.3084308,"remaining_time":35.472863,"test":[0.7298457788]},
{"learn":[0.7265382809],"iteration":591,"passed_time":100.4789105,"remaining_time":35.30340098,"test":[0.7297965173]},
{"learn":[0.7264095727],"iteration":592,"passed_time":100.6513106,"remaining_time":35.13460589,"test":[0.7297448898]},
{"learn":[0.7263438997],"iteration":593,"passed_time":100.8235134,"remaining_time":34.96573024,"test":[0.7296783532]},
{"learn":[0.7262387632],"iteration":594,"passed_time":100.9931599,"remaining_time":34.79596264,"test":[0.7296485752]},
{"learn":[0.7261821056],"iteration":595,"passed_time":101.1629838,"remaining_time":34.62625622,"test":[0.7296601554]},
{"learn":[0.7260913084],"iteration":596,"passed_time":101.3340025,"remaining_time":34.45695561,"test":[0.729636469]},
{"learn":[0.7259999011],"iteration":597,"passed_time":101.5029084,"remaining_time":34.2869356,"test":[0.7295902589]},
{"learn":[0.7259214602],"iteration":598,"passed_time":101.6723358,"remaining_time":34.11709432,"test":[0.7295421624]},
{"learn":[0.7258369407],"iteration":599,"passed_time":101.8443794,"remaining_time":33.94812648,"test":[0.7295367975]},
{"learn":[0.7257681341],"iteration":600,"passed_time":102.0126869,"remaining_time":33.77791129,"test":[0.7295186901]},
{"learn":[0.7257044241],"iteration":601,"passed_time":102.1846131,"remaining_time":33.60889268,"test":[0.7294914643]},
{"learn":[0.7256550123],"iteration":602,"passed_time":102.359615,"remaining_time":33.44086925,"test":[0.7294817676]},
{"learn":[0.7255636207],"iteration":603,"passed_time":102.5275338,"remaining_time":33.27052423,"test":[0.7294570496]},
{"learn":[0.725487973],"iteration":604,"passed_time":102.6950011,"remaining_time":33.10004168,"test":[0.7294797755]},
{"learn":[0.7254182557],"iteration":605,"passed_time":102.8587268,"remaining_time":32.92837128,"test":[0.7294349931]},
{"learn":[0.7253445928],"iteration":606,"passed_time":103.0287377,"remaining_time":32.75872548,"test":[0.7294351806]},
{"learn":[0.7252965062],"iteration":607,"passed_time":103.2009555,"remaining_time":32.58977542,"test":[0.7294456889]},
{"learn":[0.7252492629],"iteration":608,"passed_time":103.3728118,"remaining_time":32.42070125,"test":[0.7294423751]},
{"learn":[0.7251774411],"iteration":609,"passed_time":103.5409544,"remaining_time":32.2504612,"test":[0.729421462]},
{"learn":[0.7250992331],"iteration":610,"passed_time":103.7137774,"remaining_time":32.08167583,"test":[0.7293750244]},
{"learn":[0.7249686576],"iteration":611,"passed_time":103.8797178,"remaining_time":31.91076299,"test":[0.7293361259]},
{"learn":[0.7248857945],"iteration":612,"passed_time":104.0471428,"remaining_time":31.74031927,"test":[0.7293136396]},
{"learn":[0.7247611874],"iteration":613,"passed_time":104.2128497,"remaining_time":31.5693649,"test":[0.7292183606]},
{"learn":[0.7245816067],"iteration":614,"passed_time":104.3859059,"remaining_time":31.40063835,"test":[0.7292035024]},
{"learn":[0.7244335326],"iteration":615,"passed_time":104.5576698,"remaining_time":31.23151175,"test":[0.7291995182]},
{"learn":[0.7243989597],"iteration":616,"passed_time":104.7342155,"remaining_time":31.06379488,"test":[0.7292038021]},
{"learn":[0.7243140829],"iteration":617,"passed_time":104.9009625,"remaining_time":30.89316371,"test":[0.7291916803]},
{"learn":[0.7242377808],"iteration":618,"passed_time":105.0680997,"remaining_time":30.72265919,"test":[0.7291891401]},
{"learn":[0.7241898215],"iteration":619,"passed_time":105.2386365,"remaining_time":30.55315253,"test":[0.7291833306]},
{"learn":[0.7240615434],"iteration":620,"passed_time":105.4062393,"remaining_time":30.38279683,"test":[0.7290841628]},
{"learn":[0.7240074275],"iteration":621,"passed_time":105.5797618,"remaining_time":30.21414406,"test":[0.7290751149]},
{"learn":[0.7238937214],"iteration":622,"passed_time":105.754335,"remaining_time":30.04577415,"test":[0.729020062]},
{"learn":[0.72382437],"iteration":623,"passed_time":105.9201295,"remaining_time":29.87490831,"test":[0.7290229111]},
{"learn":[0.7237866951],"iteration":624,"passed_time":106.0951113,"remaining_time":29.70663116,"test":[0.7289882216]},
{"learn":[0.7237175006],"iteration":625,"passed_time":106.2664812,"remaining_time":29.53732863,"test":[0.7289891764]},
{"learn":[0.7236150215],"iteration":626,"passed_time":106.4408896,"remaining_time":29.3688579,"test":[0.7289452682]},
{"learn":[0.7235237387],"iteration":627,"passed_time":106.6103602,"remaining_time":29.19901585,"test":[0.7289732986]},
{"learn":[0.7234362354],"iteration":628,"passed_time":106.7811784,"remaining_time":29.02954134,"test":[0.7289817814]},
{"learn":[0.7233305123],"iteration":629,"passed_time":106.9573994,"remaining_time":28.86152047,"test":[0.7289856941]},
{"learn":[0.723312146],"iteration":630,"passed_time":107.1265245,"remaining_time":28.69157313,"test":[0.7289955094]},
{"learn":[0.7232588023],"iteration":631,"passed_time":107.2958405,"remaining_time":28.52167913,"test":[0.7289996481]},
{"learn":[0.7231984128],"iteration":632,"passed_time":107.481077,"remaining_time":28.35598714,"test":[0.7289829536]},
{"learn":[0.7231514062],"iteration":633,"passed_time":107.6588568,"remaining_time":28.18828113,"test":[0.7289604943]},
{"learn":[0.7231084958],"iteration":634,"passed_time":107.8400167,"remaining_time":28.02142167,"test":[0.7289410155]},
{"learn":[0.7229826998],"iteration":635,"passed_time":108.022852,"remaining_time":27.85494925,"test":[0.728932896]},
{"learn":[0.7228992288],"iteration":636,"passed_time":108.1956432,"remaining_time":27.68585533,"test":[0.7289138558]},
{"learn":[0.7228173193],"iteration":637,"passed_time":108.3678677,"remaining_time":27.5166059,"test":[0.7288816451]},
{"learn":[0.7227548376],"iteration":638,"passed_time":108.5406791,"remaining_time":27.34749506,"test":[0.7288529001]},
{"learn":[0.7226648914],"iteration":639,"passed_time":108.716007,"remaining_time":27.17900176,"test":[0.7288326011]},
{"learn":[0.7226145344],"iteration":640,"passed_time":108.8885177,"remaining_time":27.00978831,"test":[0.7288168942]},
{"learn":[0.7225407913],"iteration":641,"passed_time":109.0643895,"remaining_time":26.8413918,"test":[0.7288471069]},
{"learn":[0.7224878106],"iteration":642,"passed_time":109.2334091,"remaining_time":26.67129896,"test":[0.7288148444]},
{"learn":[0.7224321726],"iteration":643,"passed_time":109.4066111,"remaining_time":26.50222256,"test":[0.7287796251]},
{"learn":[0.7223438795],"iteration":644,"passed_time":109.5740613,"remaining_time":26.33175117,"test":[0.7287434708]},
{"learn":[0.7222795314],"iteration":645,"passed_time":109.7476031,"remaining_time":26.16274129,"test":[0.728735371]},
{"learn":[0.7221571152],"iteration":646,"passed_time":109.9168323,"remaining_time":25.9926976,"test":[0.7287088265]},
{"learn":[0.7220531833],"iteration":647,"passed_time":110.0851286,"remaining_time":25.82243758,"test":[0.7286865369]},
{"learn":[0.7219481277],"iteration":648,"passed_time":110.2645031,"remaining_time":25.65476112,"test":[0.7286857955]},
{"learn":[0.7218593081],"iteration":649,"passed_time":110.4324804,"remaining_time":25.48441855,"test":[0.7286585641]},
{"learn":[0.7215337251],"iteration":650,"passed_time":110.6117512,"remaining_time":25.3166681,"test":[0.728602111]},
{"learn":[0.7214085726],"iteration":651,"passed_time":110.7960018,"remaining_time":25.15001267,"test":[0.7285820435]},
{"learn":[0.7213034434],"iteration":652,"passed_time":110.9657628,"remaining_time":24.98004154,"test":[0.7285765347]},
{"learn":[0.7212356014],"iteration":653,"passed_time":111.1380283,"remaining_time":24.81063016,"test":[0.7285369432]},
{"learn":[0.7211703467],"iteration":654,"passed_time":111.314847,"remaining_time":24.64221803,"test":[0.7285390987]},
{"learn":[0.7211179201],"iteration":655,"passed_time":111.4876391,"remaining_time":24.47289638,"test":[0.7285126099]},
{"learn":[0.7210186925],"iteration":656,"passed_time":111.6542214,"remaining_time":24.30221258,"test":[0.7284960966]},
{"learn":[0.7208992572],"iteration":657,"passed_time":111.8202096,"remaining_time":24.13141302,"test":[0.7284339695]},
{"learn":[0.720789286],"iteration":658,"passed_time":111.9978067,"remaining_time":23.96311191,"test":[0.7283987031]},
{"learn":[0.7207192244],"iteration":659,"passed_time":112.1664824,"remaining_time":23.7928902,"test":[0.7284039236]},
{"learn":[0.7204516972],"iteration":660,"passed_time":112.3410794,"remaining_time":23.62391836,"test":[0.728388511]},
{"learn":[0.7204054639],"iteration":661,"passed_time":112.5139466,"remaining_time":23.45456893,"test":[0.7283795066]},
{"learn":[0.7203289463],"iteration":662,"passed_time":112.693684,"remaining_time":23.28662852,"test":[0.7283978647]},
{"learn":[0.7202416822],"iteration":663,"passed_time":112.8605469,"remaining_time":23.11601563,"test":[0.7284147814]},
{"learn":[0.7200096361],"iteration":664,"passed_time":113.0325534,"remaining_time":22.94645821,"test":[0.728472912]},
{"learn":[0.7199629797],"iteration":665,"passed_time":113.2022014,"remaining_time":22.7764189,"test":[0.7284700591]},
{"learn":[0.7198612686],"iteration":666,"passed_time":113.3725837,"remaining_time":22.60652719,"test":[0.7284362214]},
{"learn":[0.7198100206],"iteration":667,"passed_time":113.5390401,"remaining_time":22.43585823,"test":[0.7284226536]},
{"learn":[0.719736045],"iteration":668,"passed_time":113.7142588,"remaining_time":22.26691764,"test":[0.7284077291]},
{"learn":[0.7196509571],"iteration":669,"passed_time":113.8862474,"remaining_time":22.09733158,"test":[0.728406784]},
{"learn":[0.7195764373],"iteration":670,"passed_time":114.0603994,"remaining_time":21.92815428,"test":[0.7284272412]},
{"learn":[0.7194633998],"iteration":671,"passed_time":114.2297243,"remaining_time":21.75804271,"test":[0.7283973561]},
{"learn":[0.7193662084],"iteration":672,"passed_time":114.4034046,"remaining_time":21.58875541,"test":[0.7283921499]},
{"learn":[0.7192849358],"iteration":673,"passed_time":114.5724577,"remaining_time":21.41859002,"test":[0.7283634518]},
{"learn":[0.7192245749],"iteration":674,"passed_time":114.7421976,"remaining_time":21.24855512,"test":[0.728351131]},
{"learn":[0.7191557026],"iteration":675,"passed_time":114.9190023,"remaining_time":21.07981699,"test":[0.7283511779]},
{"learn":[0.7190593636],"iteration":676,"passed_time":115.0974184,"remaining_time":20.9113478,"test":[0.7283271273]},
{"learn":[0.7189890736],"iteration":677,"passed_time":115.2719534,"remaining_time":20.7421509,"test":[0.7282872074]},
{"learn":[0.7189228074],"iteration":678,"passed_time":115.443576,"remaining_time":20.57241928,"test":[0.7282790597]},
{"learn":[0.7187844097],"iteration":679,"passed_time":115.6164362,"remaining_time":20.40290051,"test":[0.7282537383]},
{"learn":[0.7187106033],"iteration":680,"passed_time":115.7838465,"remaining_time":20.23241958,"test":[0.7281519347]},
{"learn":[0.7186395878],"iteration":681,"passed_time":115.9774417,"remaining_time":20.06647819,"test":[0.7281141146]},
{"learn":[0.7185827639],"iteration":682,"passed_time":116.1475788,"remaining_time":19.89643736,"test":[0.7280841499]},
{"learn":[0.7185227238],"iteration":683,"passed_time":116.3212646,"remaining_time":19.72699809,"test":[0.728078878]},
{"learn":[0.7184629527],"iteration":684,"passed_time":116.4983257,"remaining_time":19.55811308,"test":[0.7280531581]},
{"learn":[0.7184121764],"iteration":685,"passed_time":116.6684798,"remaining_time":19.38805642,"test":[0.7280257297]},
{"learn":[0.7183484109],"iteration":686,"passed_time":116.8422324,"remaining_time":19.21859135,"test":[0.7280068732]},
{"learn":[0.7183143447],"iteration":687,"passed_time":117.0075984,"remaining_time":19.04774858,"test":[0.7280037941]},
{"learn":[0.7182362506],"iteration":688,"passed_time":117.1773006,"remaining_time":18.87762027,"test":[0.727997149]},
{"learn":[0.7181762043],"iteration":689,"passed_time":117.3553287,"remaining_time":18.70882052,"test":[0.7279705661]},
{"learn":[0.7180612882],"iteration":690,"passed_time":117.5294632,"remaining_time":18.53937987,"test":[0.7279408476]},
{"learn":[0.7179870849],"iteration":691,"passed_time":117.694254,"remaining_time":18.36846739,"test":[0.7279043327]},
{"learn":[0.7179272598],"iteration":692,"passed_time":117.8635036,"remaining_time":18.19826101,"test":[0.7279065524]}
]}